sample/__init__.py
sample/simple.py
sampleproject_merinhunter-0.1.0.dist-info/WHEEL
sampleproject_merinhunter-0.1.0.dist-info/METADATA
sampleproject_merinhunter-0.1.0.dist-info/RECORD
