Metadata-Version: 2.1
Name: sampleproject-merinhunter
Version: 0.1.0
Summary: A sample Python project
Home-page: https://github.com/pypa/sampleproject
License: MIT
Author: A. Random Developer
Author-email: author@example.com
Requires-Python: >=3.8,<4.0
Classifier: License :: OSI Approved :: MIT License
Classifier: Programming Language :: Python :: 3
Classifier: Programming Language :: Python :: 3.8
Classifier: Programming Language :: Python :: 3.9
Project-URL: Repository, https://github.com/pypa/sampleproject
